LICENSE.txt
MANIFEST.in
README.md
setup.cfg
setup.py
libdai/.DS_Store
libdai/AUTHORS
libdai/ChangeLog
libdai/LICENSE
libdai/Makefile
libdai/Makefile.ALL
libdai/Makefile.CYGWIN
libdai/Makefile.LINUX
libdai/Makefile.MACOSX
libdai/Makefile.MACOSX64
libdai/Makefile.WINDOWS
libdai/Makefile.WINDOWS64
libdai/Makefile.conf
libdai/README
libdai/alldai.o
libdai/bbp.o
libdai/bipgraph.o
libdai/bp.o
libdai/bp_dual.o
libdai/cbp.o
libdai/clustergraph.o
libdai/cobwebgraph.o
libdai/customdoxygen.css
libdai/dag.o
libdai/daialg.o
libdai/decmap.o
libdai/dfactor.o
libdai/doxygen.conf
libdai/emalg.o
libdai/evidence.o
libdai/exactinf.o
libdai/exceptions.o
libdai/factor.o
libdai/factorgraph.o
libdai/fbp.o
libdai/gibbs.o
libdai/glc.o
libdai/graph.o
libdai/hak.o
libdai/io.o
libdai/jtree.o
libdai/lc.o
libdai/mf.o
libdai/mr.o
libdai/properties.o
libdai/regiongraph.o
libdai/tbp.o
libdai/treeep.o
libdai/trwbp.o
libdai/util.o
libdai/varset.o
libdai/weightedgraph.o
libdai/include/dai/alldai.h
libdai/include/dai/bbp.h
libdai/include/dai/bipgraph.h
libdai/include/dai/bp.h
libdai/include/dai/bp_dual.h
libdai/include/dai/cbp.h
libdai/include/dai/clustergraph.h
libdai/include/dai/cobwebgraph.h
libdai/include/dai/dag.h
libdai/include/dai/dai_config.h
libdai/include/dai/daialg.h
libdai/include/dai/decmap.h
libdai/include/dai/dfactor.h
libdai/include/dai/dfactor_macros.h
libdai/include/dai/doc.h
libdai/include/dai/emalg.h
libdai/include/dai/enum.h
libdai/include/dai/evidence.h
libdai/include/dai/exactinf.h
libdai/include/dai/exceptions.h
libdai/include/dai/factor.h
libdai/include/dai/factorgraph.h
libdai/include/dai/fbp.h
libdai/include/dai/gibbs.h
libdai/include/dai/glc.h
libdai/include/dai/graph.h
libdai/include/dai/hak.h
libdai/include/dai/index.h
libdai/include/dai/io.h
libdai/include/dai/jtree.h
libdai/include/dai/lc.h
libdai/include/dai/mf.h
libdai/include/dai/mr.h
libdai/include/dai/prob.h
libdai/include/dai/properties.h
libdai/include/dai/realfactor.h
libdai/include/dai/regiongraph.h
tbp.egg-info/PKG-INFO
tbp.egg-info/SOURCES.txt
tbp.egg-info/dependency_links.txt
tbp.egg-info/entry_points.txt
tbp.egg-info/requires.txt
tbp.egg-info/top_level.txt