Metadata-Version: 2.1
Name: tbp
Version: 0.1.1
Summary: Tensor Belief Propagation - algorithm for approximate inference in discrete graphical models
Home-page: https://github.com/akxlr/tbp
Author: Andrew Wrigley
Author-email: andrew@wrigley.io
Maintainer: Andrew Wrigley
Maintainer-email: andrew@wrigley.io
License: MIT
Download-URL: https://github.com/akxlr/tbp/archive/0.1.1.tar.gz
Keywords: tensor,belief,propagation,tensor belief propagation,graphical models,machine learning,inference
Platform: UNKNOWN
Classifier: Development Status :: 3 - Alpha
Classifier: Environment :: Console
Classifier: Intended Audience :: Science/Research
Classifier: License :: OSI Approved :: MIT License
Classifier: Operating System :: MacOS :: MacOS X
Classifier: Operating System :: POSIX :: Linux
Classifier: Operating System :: Unix
Classifier: Programming Language :: C++
Classifier: Programming Language :: Python :: 3 :: Only
Classifier: Topic :: Scientific/Engineering :: Artificial Intelligence
